freekassa/__init__.py
freekassa/api.py
free_kassa_py-1.0.2.dist-info/METADATA
free_kassa_py-1.0.2.dist-info/WHEEL
free_kassa_py-1.0.2.dist-info/top_level.txt
free_kassa_py-1.0.2.dist-info/RECORD
