Metadata-Version: 2.1
Name: free-kassa-py
Version: 1.0.2
Summary: FreeKassa python 3 client
Home-page: https://github.com/Churakovmike/free-kassa-py
Author: Mikhail Churakov
Author-email: churakovmike@mail.ru
License: UNKNOWN
Project-URL: Source, https://github.com/Churakovmike/free-kassa-py
Keywords: freekassa
Platform: UNKNOWN
Classifier: Development Status :: 4 - Beta
Classifier: Intended Audience :: Developers
Classifier: License :: OSI Approved :: Apache Software License
Classifier: Programming Language :: Python :: 3.4
Classifier: Programming Language :: Python :: 3.5
Classifier: Programming Language :: Python :: 3.6
Classifier: Programming Language :: Python :: 3.7
Classifier: Programming Language :: Python :: 3.8
Requires-Python: >3.4
